AUTHORS.rst
CHANGELOG.rst
LICENSE
MANIFEST.in
README.rst
setup.py
contact/__init__.py
contact/admin.py
contact/forms.py
contact/models.py
contact/urls.py
contact/views.py
contact/locale/af/LC_MESSAGES/django.mo
contact/locale/af/LC_MESSAGES/django.po
contact/locale/fr/LC_MESSAGES/django.mo
contact/locale/fr/LC_MESSAGES/django.po
contact/templates/contact/site_contact.html
contact/tests/__init__.py
contact/tests/__init__.pyc
contact/tests/requirements.txt
contact/tests/urls.py
contact/tests/urls.pyc
jmbo_contact.egg-info/PKG-INFO
jmbo_contact.egg-info/SOURCES.txt
jmbo_contact.egg-info/dependency_links.txt
jmbo_contact.egg-info/not-zip-safe
jmbo_contact.egg-info/requires.txt
jmbo_contact.egg-info/top_level.txt